{"cameraMode":{"drawMode":0,"name":"Shaded","section":"Shading Mode"},"sceneLighting":true,"audioPlay":false,"sceneViewState":{"showFog":true,"showMaterialUpdate":false,"showSkybox":true,"showFlares":true,"showImageEffects":true,"showParticleSystems":true},"in2DMode":false,"pivot":{"x":23.730514526367189,"y":1.297997236251831,"z":-45.21916961669922},"rotation":{"x":0.0022322789300233127,"y":0.9926013350486755,"z":0.018466638401150705,"w":-0.11998584866523743},"size":4.804279327392578,"orthographic":false}